submissions/2023B3A31122G_stopwatch/rtl/stopwatch_top.v
module stopwatch_top (
    input  wire       clk,
    input  wire       rst_n,    // Active-low hardware reset
    input  wire       start,    // Start button
    input  wire       stop,     // Stop button
    input  wire       reset,    // User Reset button (Active-high)
    output wire [7:0] minutes,  // 00-120
    output wire [5:0] seconds,  // 00-59
    output wire [1:0] status    // 00=IDLE, 01=RUNNING, 10=PAUSED
);


    
    //Combining the hardware reset[Active-low] and user reset[Active-high]
    wire system_rst_n;
    assign system_rst_n = rst_n & (~reset); //taking the complement of reset to make it active-low

    
    wire enable_counting; // From FSM to Seconds Counter
    wire seconds_roll;    // From Seconds (at 59) to Minutes Counter
    wire minutes_end;     // From Minutes (at 120) to Seconds Counter

    
    //Module Instantinations
    

    // Control FSM
    
    control_fsm fsm_inst (
        .clk(clk),
        .rst_n(rst_n),        // FSM only resets on hard reset, handles the reset input internally
        .start(start),
        .stop(stop),
        .reset(reset),        
        .enable(enable_counting),
        .status(status)
    );

    //Seconds Counter (0-59)
    
    seconds_counter sec_inst (
        .clk(clk),
        .rst_n(system_rst_n), // Reset if hardware reset or user reset is pressed
        .enable(enable_counting),
        .min_end(minutes_end),// Reset when minutes reach 120
        .seconds(seconds),    
        .roll(seconds_roll)   // Output signal when seconds = 59
    );

    // Minutes Counter (0-120)
    
    minutes_counter min_inst (
        .clk(clk),
        .rst_n(system_rst_n), // Reset if hardware reset or user reset is pressed
        .enable(seconds_roll),// Connects to the rollover signal from seconds
        .minutes(minutes),    
        .min_end(minutes_end) // Output signal when minutes reach 120
    );

endmodule

module jk_flip_flop (
    input wire clk,
    input wire rst,
    input wire j,
    input wire k,
    output reg q
);
    always @(posedge clk or posedge rst) begin
        if (rst) begin
            q <= 1'b0;
        end else begin
            case ({j, k})
                2'b00: q <= q;      // Hold
                2'b01: q <= 1'b0;   // Reset
                2'b10: q <= 1'b1;   // Set
                2'b11: q <= ~q;     // Toggle
            endcase
        end
    end
endmodule

submissions/2023B3A31122G_stopwatch/rtl/minutes_counter.v
module minutes_counter (
    input  wire       clk,
    input  wire       rst_n,    // Active low system reset 
    input  wire       enable,   // The roll output from the seconds counter
    output wire [7:0] minutes,
    output wire       min_end   // Output signal when minutes = 120
);

    
    wire [7:0] Q;           // flip flop outputs
    wire       rst_combined;// The output of the OR gate [system reset + rollover reset + minute reset]
    
    // JK Input logic
    wire j0, j1, j2, j3, j4, j5, j6, j7;
    
    assign j0 = enable;        // LSB to the roll signal from seconds counter
    assign j1 = Q[0] & j0;     // AND gate for FF1
    assign j2 = Q[1] & j1;     // AND gate for FF2
    assign j3 = Q[2] & j2;     // AND gate for FF3
    assign j4 = Q[3] & j3;     // AND gate for FF4
    assign j5 = Q[4] & j4;     // AND gate for FF5
    assign j6 = Q[5] & j5;     // AND gate for FF6
    assign j7 = Q[6] & j6;     // AND gate for FF7

   //Reset Logic
    
    
    assign min_end = Q[6] & Q[5] & Q[4] & Q[3];// Reset when minutes reach 120 

    
    assign rst_combined = min_end | (~rst_n);//Comining Resets

    // flip flop instantiation
    
    jk_flip_flop ff0 (.clk(clk), .rst(rst_combined), .j(j0), .k(j0), .q(Q[0]));
    jk_flip_flop ff1 (.clk(clk), .rst(rst_combined), .j(j1), .k(j1), .q(Q[1]));
    jk_flip_flop ff2 (.clk(clk), .rst(rst_combined), .j(j2), .k(j2), .q(Q[2]));
    jk_flip_flop ff3 (.clk(clk), .rst(rst_combined), .j(j3), .k(j3), .q(Q[3]));
    jk_flip_flop ff4 (.clk(clk), .rst(rst_combined), .j(j4), .k(j4), .q(Q[4]));
    jk_flip_flop ff5 (.clk(clk), .rst(rst_combined), .j(j5), .k(j5), .q(Q[5]));
    jk_flip_flop ff6 (.clk(clk), .rst(rst_combined), .j(j6), .k(j6), .q(Q[6]));
    jk_flip_flop ff7 (.clk(clk), .rst(rst_combined), .j(j7), .k(j7), .q(Q[7]));

    // Output assignment
    assign minutes = Q;

endmodule

submissions/2023B3A31122G_stopwatch/rtl/seconds_counter.v
module seconds_counter (
    input  wire       clk,
    input  wire       rst_n,   // Active low system reset 
    input  wire       enable,  //Running signal from fsm
    input  wire       min_end, // Reset when minutes reach 120
    output wire [5:0] seconds,
    output wire       roll     // Output signal when seconds = 59
);

    
    wire [5:0] Q;        // flipflop outputs
   
    wire       rst_combined; // The output of the OR gate [system reset + rollover reset + minute reset]
    
    //JK Input logic
    wire j0, j1, j2, j3, j4, j5;
    
    assign j0 = enable;
    assign j1 = Q[0] & j0;      // AND gate for FF1
    assign j2 = Q[1] & j1;      // AND gate for FF2
    assign j3 = Q[2] & j2;      // AND gate for FF3
    assign j4 = Q[3] & j3;      // AND gate for FF4
    assign j5 = Q[4] & j4;      // AND gate for FF5

 //Reset Logic
    
    
    assign roll = Q[5] & Q[4] & Q[3] & Q[1]& Q[0]; //When seconds =59 value changes to 1. Since roll acts as the enable for minutes counter, at the very next positive edge the flip flop will toggle.
    wire reset_60= Q[5] & Q[4] & Q[3] & Q[2];

   
    assign rst_combined = reset_60 | (~rst_n) | min_end; //Combining the resets

    // flip flop instantiation
    
    
    
    
    jk_flip_flop ff0 (.clk(clk), .rst(rst_combined), .j(j0), .k(j0), .q(Q[0]));
    jk_flip_flop ff1 (.clk(clk), .rst(rst_combined), .j(j1), .k(j1), .q(Q[1]));
    jk_flip_flop ff2 (.clk(clk), .rst(rst_combined), .j(j2), .k(j2), .q(Q[2]));
    jk_flip_flop ff3 (.clk(clk), .rst(rst_combined), .j(j3), .k(j3), .q(Q[3]));
    jk_flip_flop ff4 (.clk(clk), .rst(rst_combined), .j(j4), .k(j4), .q(Q[4]));
    jk_flip_flop ff5 (.clk(clk), .rst(rst_combined), .j(j5), .k(j5), .q(Q[5]));

    // Output assignment
    assign seconds = Q;

endmodule

submissions/2023B3A31122G_stopwatch/rtl/control_fsm.v
module control_fsm (
    input  wire       clk,
    input  wire       rst_n,      // Active-low hardware reset
    input  wire       start,      // Start button 
    input  wire       stop,       // Stop button 
    input  wire       reset,      // User Reset button 
    output wire       enable,     // 1 = Count, 0 = Hold
    output reg  [1:0] status      // 00=IDLE, 01=RUNNING, 10=PAUSED
);

    //State definitions
    localparam STATE_IDLE    = 2'b00;
    localparam STATE_RUNNING = 2'b01;
    localparam STATE_PAUSED  = 2'b10;

    // Internal state register
    reg [1:0] current_state, next_state;

   
    //Current state Logic
   
    always @(posedge clk or negedge rst_n) begin
        if (!rst_n) begin
            current_state <= STATE_IDLE;
        end else begin
            // User reset forces IDLE
            if (reset)
                current_state <= STATE_IDLE;
            else
                current_state <= next_state;
        end
    end

    
    //  Next State Logic
    
    always @(*) begin
        // Default to staying in the current state
        next_state = current_state;

        case (current_state)
            STATE_IDLE: begin
                // If Start is pressed, start running
                if (start) 
                    next_state = STATE_RUNNING;
            end

            STATE_RUNNING: begin
                // If Stop is pressed, pause the watch
                if (stop) 
                    next_state = STATE_PAUSED;
               
            end

            STATE_PAUSED: begin
                // If Start is pressed again, continue running
                if (start) 
                    next_state = STATE_RUNNING;
            end
            
            default: next_state = STATE_IDLE;
        endcase
    end

   //Output Logic
    
    // Update the status output to match the current state
    always @(*) begin
        status = current_state;
    end

    //enable signal is high only when we are running the stopwatch
    assign enable = (current_state == STATE_RUNNING);

endmodule

submissions/2023B3A31122G_stopwatch/tb/tb.v
`timescale 1ns/1ps

module tb_stopwatch();
    // Inputs 
    reg clk;
    reg rst_n;
    reg start;
    reg stop;
    reg reset;

    // Outputs 
    wire [7:0] minutes;
    wire [5:0] seconds;
    wire [1:0] status;

    // Instantiate the Top Level Module
    stopwatch_top uut (
        .clk(clk),
        .rst_n(rst_n),
        .start(start),
        .stop(stop),
        .reset(reset),
        .minutes(minutes),
        .seconds(seconds),
        .status(status)
    );

    // Generate clock, toggles every 5 units
    always #5 clk = ~clk;

    initial begin
        // Setup for GTKWave
        $dumpfile("stopwatch_sim.vcd");
        $dumpvars(0, tb_stopwatch);

        // Initialising inputs
        clk = 0;
        rst_n = 0;   // Hardware reset active
        start = 0;
        stop = 0;
        reset = 0;

        //Release hardware reset
        #20 rst_n = 1;
        
        // Testing the START button (Pulse for 1 cycle)
        #20 start = 1; #10 start = 0;
        $display("Status: RUNNING. Waiting for seconds to count...");

        // Wait to see several seconds 
        #1000; 

        //Testing the STOP/PAUSE button
        #20 stop = 1; #10 stop = 0;
        $display("Status: PAUSED. Checking if time is retained...");
        #100;

        // Testing the RESUME button
        #20 start = 1; #10 start = 0;
        #100;

        // Testing the RESET Button
        #20 reset = 1; #10 reset = 0;
        $display("Status: IDLE. Time should be 00:00.");

        #100;
        $finish;
    end
endmodule

submissions/2023B3A31122G_stopwatch/stopwatch_sim.vcd
$date
	Sun Feb  1 16:38:56 2026
$end
$version
	Icarus Verilog
$end
$timescale
	1ps
$end
$scope module tb_stopwatch $end
$var wire 2 ! status [1:0] $end
$var wire 6 " seconds [5:0] $end
$var wire 8 # minutes [7:0] $end
$var reg 1 $ clk $end
$var reg 1 % reset $end
$var reg 1 & rst_n $end
$var reg 1 ' start $end
$var reg 1 ( stop $end
$scope module uut $end
$var wire 1 $ clk $end
$var wire 1 % reset $end
$var wire 1 & rst_n $end
$var wire 1 ' start $end
$var wire 1 ( stop $end
$var wire 1 ) system_rst_n $end
$var wire 2 * status [1:0] $end
$var wire 1 + seconds_roll $end
$var wire 6 , seconds [5:0] $end
$var wire 1 - minutes_end $end
$var wire 8 . minutes [7:0] $end
$var wire 1 / enable_counting $end
$scope module fsm_inst $end
$var wire 1 $ clk $end
$var wire 1 % reset $end
$var wire 1 & rst_n $end
$var wire 1 ' start $end
$var wire 1 ( stop $end
$var wire 1 / enable $end
$var parameter 2 0 STATE_IDLE $end
$var parameter 2 1 STATE_PAUSED $end
$var parameter 2 2 STATE_RUNNING $end
$var reg 2 3 current_state [1:0] $end
$var reg 2 4 next_state [1:0] $end
$var reg 2 5 status [1:0] $end
$upscope $end
$scope module min_inst $end
$var wire 1 $ clk $end
$var wire 1 6 j0 $end
$var wire 1 7 j1 $end
$var wire 1 8 j2 $end
$var wire 1 9 j3 $end
$var wire 1 : j4 $end
$var wire 1 ; j5 $end
$var wire 1 < j6 $end
$var wire 1 = j7 $end
$var wire 1 - min_end $end
$var wire 8 > minutes [7:0] $end
$var wire 1 ? rst_combined $end
$var wire 1 ) rst_n $end
$var wire 1 + enable $end
$var wire 8 @ Q [7:0] $end
$scope module ff0 $end
$var wire 1 $ clk $end
$var wire 1 6 j $end
$var wire 1 6 k $end
$var wire 1 ? rst $end
$var reg 1 A q $end
$upscope $end
$scope module ff1 $end
$var wire 1 $ clk $end
$var wire 1 7 j $end
$var wire 1 7 k $end
$var wire 1 ? rst $end
$var reg 1 B q $end
$upscope $end
$scope module ff2 $end
$var wire 1 $ clk $end
$var wire 1 8 j $end
$var wire 1 8 k $end
$var wire 1 ? rst $end
$var reg 1 C q $end
$upscope $end
$scope module ff3 $end
$var wire 1 $ clk $end
$var wire 1 9 j $end
$var wire 1 9 k $end
$var wire 1 ? rst $end
$var reg 1 D q $end
$upscope $end
$scope module ff4 $end
$var wire 1 $ clk $end
$var wire 1 : j $end
$var wire 1 : k $end
$var wire 1 ? rst $end
$var reg 1 E q $end
$upscope $end
$scope module ff5 $end
$var wire 1 $ clk $end
$var wire 1 ; j $end
$var wire 1 ; k $end
$var wire 1 ? rst $end
$var reg 1 F q $end
$upscope $end
$scope module ff6 $end
$var wire 1 $ clk $end
$var wire 1 < j $end
$var wire 1 < k $end
$var wire 1 ? rst $end
$var reg 1 G q $end
$upscope $end
$scope module ff7 $end
$var wire 1 $ clk $end
$var wire 1 = j $end
$var wire 1 = k $end
$var wire 1 ? rst $end
$var reg 1 H q $end
$upscope $end
$upscope $end
$scope module sec_inst $end
$var wire 1 $ clk $end
$var wire 1 / enable $end
$var wire 1 I j0 $end
$var wire 1 J j1 $end
$var wire 1 K j2 $end
$var wire 1 L j3 $end
$var wire 1 M j4 $end
$var wire 1 N j5 $end
$var wire 1 - min_end $end
$var wire 1 O reset_60 $end
$var wire 1 + roll $end
$var wire 1 P rst_combined $end
$var wire 1 ) rst_n $end
$var wire 6 Q seconds [5:0] $end
$var wire 6 R Q [5:0] $end
$scope module ff0 $end
$var wire 1 $ clk $end
$var wire 1 I j $end
$var wire 1 I k $end
$var wire 1 P rst $end
$var reg 1 S q $end
$upscope $end
$scope module ff1 $end
$var wire 1 $ clk $end
$var wire 1 J j $end
$var wire 1 J k $end
$var wire 1 P rst $end
$var reg 1 T q $end
$upscope $end
$scope module ff2 $end
$var wire 1 $ clk $end
$var wire 1 K j $end
$var wire 1 K k $end
$var wire 1 P rst $end
$var reg 1 U q $end
$upscope $end
$scope module ff3 $end
$var wire 1 $ clk $end
$var wire 1 L j $end
$var wire 1 L k $end
$var wire 1 P rst $end
$var reg 1 V q $end
$upscope $end
$scope module ff4 $end
$var wire 1 $ clk $end
$var wire 1 M j $end
$var wire 1 M k $end
$var wire 1 P rst $end
$var reg 1 W q $end
$upscope $end
$scope module ff5 $end
$var wire 1 $ clk $end
$var wire 1 N j $end
$var wire 1 N k $end
$var wire 1 P rst $end
$var reg 1 X q $end
$upscope $end
$upscope $end
$upscope $end
$upscope $end
$enddefinitions $end
$comment Show the parameter values. $end
$dumpall
b1 2
b10 1
b0 0
$end
#0
$dumpvars
0X
0W
0V
0U
0T
0S
b0 R
b0 Q
1P
0O
0N
0M
0L
0K
0J
0I
0H
0G
0F
0E
0D
0C
0B
0A
b0 @
1?
b0 >
0=
0<
0;
0:
09
08
07
06
b0 5
b0 4
b0 3
0/
b0 .
0-
b0 ,
0+
b0 *
0)
0(
0'
0&
0%
0$
b0 #
b0 "
b0 !
$end
#5000
1$
#10000
0$
#15000
1$
#20000
0P
0?
1)
0$
1&
#25000
1$
#30000
0$
#35000
1$
#40000
b1 4
0$
1'
#45000
b1 !
b1 *
b1 5
1I
1/
b1 3
1$
#50000
0$
0'
#55000
1J
b1 "
b1 ,
b1 Q
b1 R
1S
1$
#60000
0$
#65000
0J
1T
b10 "
b10 ,
b10 Q
b10 R
0S
1$
#70000
0$
#75000
1K
1J
b11 "
b11 ,
b11 Q
b11 R
1S
1$
#80000
0$
#85000
0K
0J
1U
0T
b100 "
b100 ,
b100 Q
b100 R
0S
1$
#90000
0$
#95000
1J
b101 "
b101 ,
b101 Q
b101 R
1S
1$
#100000
0$
#105000
0J
1T
b110 "
b110 ,
b110 Q
b110 R
0S
1$
#110000
0$
#115000
1L
1K
1J
b111 "
b111 ,
b111 Q
b111 R
1S
1$
#120000
0$
#125000
0L
0K
0J
1V
0U
0T
b1000 "
b1000 ,
b1000 Q
b1000 R
0S
1$
#130000
0$
#135000
1J
b1001 "
b1001 ,
b1001 Q
b1001 R
1S
1$
#140000
0$
#145000
0J
1T
b1010 "
b1010 ,
b1010 Q
b1010 R
0S
1$
#150000
0$
#155000
1K
1J
b1011 "
b1011 ,
b1011 Q
b1011 R
1S
1$
#160000
0$
#165000
0K
0J
1U
0T
b1100 "
b1100 ,
b1100 Q
b1100 R
0S
1$
#170000
0$
#175000
1J
b1101 "
b1101 ,
b1101 Q
b1101 R
1S
1$
#180000
0$
#185000
0J
1T
b1110 "
b1110 ,
b1110 Q
b1110 R
0S
1$
#190000
0$
#195000
1M
1L
1K
1J
b1111 "
b1111 ,
b1111 Q
b1111 R
1S
1$
#200000
0$
#205000
0M
0L
0K
0J
1W
0V
0U
0T
b10000 "
b10000 ,
b10000 Q
b10000 R
0S
1$
#210000
0$
#215000
1J
b10001 "
b10001 ,
b10001 Q
b10001 R
1S
1$
#220000
0$
#225000
0J
1T
b10010 "
b10010 ,
b10010 Q
b10010 R
0S
1$
#230000
0$
#235000
1K
1J
b10011 "
b10011 ,
b10011 Q
b10011 R
1S
1$
#240000
0$
#245000
0K
0J
1U
0T
b10100 "
b10100 ,
b10100 Q
b10100 R
0S
1$
#250000
0$
#255000
1J
b10101 "
b10101 ,
b10101 Q
b10101 R
1S
1$
#260000
0$
#265000
0J
1T
b10110 "
b10110 ,
b10110 Q
b10110 R
0S
1$
#270000
0$
#275000
1L
1K
1J
b10111 "
b10111 ,
b10111 Q
b10111 R
1S
1$
#280000
0$
#285000
0L
0K
0J
1V
0U
0T
b11000 "
b11000 ,
b11000 Q
b11000 R
0S
1$
#290000
0$
#295000
1J
b11001 "
b11001 ,
b11001 Q
b11001 R
1S
1$
#300000
0$
#305000
0J
1T
b11010 "
b11010 ,
b11010 Q
b11010 R
0S
1$
#310000
0$
#315000
1K
1J
b11011 "
b11011 ,
b11011 Q
b11011 R
1S
1$
#320000
0$
#325000
0K
0J
1U
0T
b11100 "
b11100 ,
b11100 Q
b11100 R
0S
1$
#330000
0$
#335000
1J
b11101 "
b11101 ,
b11101 Q
b11101 R
1S
1$
#340000
0$
#345000
0J
1T
b11110 "
b11110 ,
b11110 Q
b11110 R
0S
1$
#350000
0$
#355000
1N
1M
1L
1K
1J
b11111 "
b11111 ,
b11111 Q
b11111 R
1S
1$
#360000
0$
#365000
0N
0M
0L
0K
0J
1X
0W
0V
0U
0T
b100000 "
b100000 ,
b100000 Q
b100000 R
0S
1$
#370000
0$
#375000
1J
b100001 "
b100001 ,
b100001 Q
b100001 R
1S
1$
#380000
0$
#385000
0J
1T
b100010 "
b100010 ,
b100010 Q
b100010 R
0S
1$
#390000
0$
#395000
1K
1J
b100011 "
b100011 ,
b100011 Q
b100011 R
1S
1$
#400000
0$
#405000
0K
0J
1U
0T
b100100 "
b100100 ,
b100100 Q
b100100 R
0S
1$
#410000
0$
#415000
1J
b100101 "
b100101 ,
b100101 Q
b100101 R
1S
1$
#420000
0$
#425000
0J
1T
b100110 "
b100110 ,
b100110 Q
b100110 R
0S
1$
#430000
0$
#435000
1L
1K
1J
b100111 "
b100111 ,
b100111 Q
b100111 R
1S
1$
#440000
0$
#445000
0L
0K
0J
1V
0U
0T
b101000 "
b101000 ,
b101000 Q
b101000 R
0S
1$
#450000
0$
#455000
1J
b101001 "
b101001 ,
b101001 Q
b101001 R
1S
1$
#460000
0$
#465000
0J
1T
b101010 "
b101010 ,
b101010 Q
b101010 R
0S
1$
#470000
0$
#475000
1K
1J
b101011 "
b101011 ,
b101011 Q
b101011 R
1S
1$
#480000
0$
#485000
0K
0J
1U
0T
b101100 "
b101100 ,
b101100 Q
b101100 R
0S
1$
#490000
0$
#495000
1J
b101101 "
b101101 ,
b101101 Q
b101101 R
1S
1$
#500000
0$
#505000
0J
1T
b101110 "
b101110 ,
b101110 Q
b101110 R
0S
1$
#510000
0$
#515000
1M
1L
1K
1J
b101111 "
b101111 ,
b101111 Q
b101111 R
1S
1$
#520000
0$
#525000
0M
0L
0K
0J
1W
0V
0U
0T
b110000 "
b110000 ,
b110000 Q
b110000 R
0S
1$
#530000
0$
#535000
1J
b110001 "
b110001 ,
b110001 Q
b110001 R
1S
1$
#540000
0$
#545000
0J
1T
b110010 "
b110010 ,
b110010 Q
b110010 R
0S
1$
#550000
0$
#555000
1K
1J
b110011 "
b110011 ,
b110011 Q
b110011 R
1S
1$
#560000
0$
#565000
0K
0J
1U
0T
b110100 "
b110100 ,
b110100 Q
b110100 R
0S
1$
#570000
0$
#575000
1J
b110101 "
b110101 ,
b110101 Q
b110101 R
1S
1$
#580000
0$
#585000
0J
1T
b110110 "
b110110 ,
b110110 Q
b110110 R
0S
1$
#590000
0$
#595000
1L
1K
1J
b110111 "
b110111 ,
b110111 Q
b110111 R
1S
1$
#600000
0$
#605000
0L
0K
0J
1V
0U
0T
b111000 "
b111000 ,
b111000 Q
b111000 R
0S
1$
#610000
0$
#615000
1J
b111001 "
b111001 ,
b111001 Q
b111001 R
1S
1$
#620000
0$
#625000
0J
1T
b111010 "
b111010 ,
b111010 Q
b111010 R
0S
1$
#630000
0$
#635000
1K
16
1+
1J
b111011 "
b111011 ,
b111011 Q
b111011 R
1S
1$
#640000
0$
#645000
0V
0W
0X
0P
0O
0K
06
0+
0J
b1 #
b1 .
b1 >
b1 @
1A
0U
0T
b0 "
b0 ,
b0 Q
b0 R
0S
1$
#650000
0$
#655000
1J
b1 "
b1 ,
b1 Q
b1 R
1S
1$
#660000
0$
#665000
0J
0K
0S
b10 "
b10 ,
b10 Q
b10 R
1T
1$
#670000
0$
#675000
1K
1J
b11 "
b11 ,
b11 Q
b11 R
1S
1$
#680000
0$
#685000
0J
0K
0L
0S
0T
b100 "
b100 ,
b100 Q
b100 R
1U
1$
#690000
0$
#695000
1J
b101 "
b101 ,
b101 Q
b101 R
1S
1$
#700000
0$
#705000
0L
0J
0K
0S
b110 "
b110 ,
b110 Q
b110 R
1T
1$
#710000
0$
#715000
1L
1K
1J
b111 "
b111 ,
b111 Q
b111 R
1S
1$
#720000
0$
#725000
0J
0K
0L
0M
0S
0T
0U
b1000 "
b1000 ,
b1000 Q
b1000 R
1V
1$
#730000
0$
#735000
1J
b1001 "
b1001 ,
b1001 Q
b1001 R
1S
1$
#740000
0$
#745000
0J
0K
0S
b1010 "
b1010 ,
b1010 Q
b1010 R
1T
1$
#750000
0$
#755000
1K
1J
b1011 "
b1011 ,
b1011 Q
b1011 R
1S
1$
#760000
0$
#765000
0M
0J
0K
0L
0S
0T
b1100 "
b1100 ,
b1100 Q
b1100 R
1U
1$
#770000
0$
#775000
1J
b1101 "
b1101 ,
b1101 Q
b1101 R
1S
1$
#780000
0$
#785000
0M
0L
0J
0K
0S
b1110 "
b1110 ,
b1110 Q
b1110 R
1T
1$
#790000
0$
#795000
1M
1L
1K
1J
b1111 "
b1111 ,
b1111 Q
b1111 R
1S
1$
#800000
0$
#805000
0J
0K
0L
0M
0N
0S
0T
0U
0V
b10000 "
b10000 ,
b10000 Q
b10000 R
1W
1$
#810000
0$
#815000
1J
b10001 "
b10001 ,
b10001 Q
b10001 R
1S
1$
#820000
0$
#825000
0J
0K
0S
b10010 "
b10010 ,
b10010 Q
b10010 R
1T
1$
#830000
0$
#835000
1K
1J
b10011 "
b10011 ,
b10011 Q
b10011 R
1S
1$
#840000
0$
#845000
0J
0K
0L
0S
0T
b10100 "
b10100 ,
b10100 Q
b10100 R
1U
1$
#850000
0$
#855000
1J
b10101 "
b10101 ,
b10101 Q
b10101 R
1S
1$
#860000
0$
#865000
0L
0J
0K
0S
b10110 "
b10110 ,
b10110 Q
b10110 R
1T
1$
#870000
0$
#875000
1L
1K
1J
b10111 "
b10111 ,
b10111 Q
b10111 R
1S
1$
#880000
0$
#885000
0N
0J
0K
0L
0M
0S
0T
0U
b11000 "
b11000 ,
b11000 Q
b11000 R
1V
1$
#890000
0$
#895000
1J
b11001 "
b11001 ,
b11001 Q
b11001 R
1S
1$
#900000
0$
#905000
0J
0K
0S
b11010 "
b11010 ,
b11010 Q
b11010 R
1T
1$
#910000
0$
#915000
1K
1J
b11011 "
b11011 ,
b11011 Q
b11011 R
1S
1$
#920000
0$
#925000
0N
0M
0J
0K
0L
0S
0T
b11100 "
b11100 ,
b11100 Q
b11100 R
1U
1$
#930000
0$
#935000
1J
b11101 "
b11101 ,
b11101 Q
b11101 R
1S
1$
#940000
0$
#945000
0N
0M
0L
0J
0K
0S
b11110 "
b11110 ,
b11110 Q
b11110 R
1T
1$
#950000
0$
#955000
1N
1M
1L
1K
1J
b11111 "
b11111 ,
b11111 Q
b11111 R
1S
1$
#960000
0$
#965000
0J
0K
0L
0M
0N
0S
0T
0U
0V
0W
b100000 "
b100000 ,
b100000 Q
b100000 R
1X
1$
#970000
0$
#975000
1J
b100001 "
b100001 ,
b100001 Q
b100001 R
1S
1$
#980000
0$
#985000
0J
0K
0S
b100010 "
b100010 ,
b100010 Q
b100010 R
1T
1$
#990000
0$
#995000
1K
1J
b100011 "
b100011 ,
b100011 Q
b100011 R
1S
1$
#1000000
0$
#1005000
0J
0K
0L
0S
0T
b100100 "
b100100 ,
b100100 Q
b100100 R
1U
1$
#1010000
0$
#1015000
1J
b100101 "
b100101 ,
b100101 Q
b100101 R
1S
1$
#1020000
0$
#1025000
0L
0J
0K
0S
b100110 "
b100110 ,
b100110 Q
b100110 R
1T
1$
#1030000
0$
#1035000
1L
1K
1J
b100111 "
b100111 ,
b100111 Q
b100111 R
1S
1$
#1040000
0$
#1045000
0J
0K
0L
0M
0S
0T
0U
b101000 "
b101000 ,
b101000 Q
b101000 R
1V
1$
#1050000
0$
#1055000
1J
b101001 "
b101001 ,
b101001 Q
b101001 R
1S
1$
#1060000
0$
#1065000
0J
0K
0S
b101010 "
b101010 ,
b101010 Q
b101010 R
1T
1$
#1070000
b10 4
0$
1(
#1075000
b10 !
b10 *
b10 5
0I
0/
b10 3
b101011 "
b101011 ,
b101011 Q
b101011 R
1S
1$
#1080000
0$
0(
#1085000
1$
#1090000
0$
#1095000
1$
#1100000
0$
#1105000
1$
#1110000
0$
#1115000
1$
#1120000
0$
#1125000
1$
#1130000
0$
#1135000
1$
#1140000
0$
#1145000
1$
#1150000
0$
#1155000
1$
#1160000
0$
#1165000
1$
#1170000
0$
#1175000
1$
#1180000
0$
#1185000
1$
#1190000
0$
#1195000
1$
#1200000
b1 4
0$
1'
#1205000
1K
b1 !
b1 *
b1 5
1J
1I
1/
b1 3
1$
#1210000
0$
0'
#1215000
0K
0J
1U
0T
b101100 "
b101100 ,
b101100 Q
b101100 R
0S
1$
#1220000
0$
#1225000
1J
b101101 "
b101101 ,
b101101 Q
b101101 R
1S
1$
#1230000
0$
#1235000
0J
1T
b101110 "
b101110 ,
b101110 Q
b101110 R
0S
1$
#1240000
0$
#1245000
1M
1L
1K
1J
b101111 "
b101111 ,
b101111 Q
b101111 R
1S
1$
#1250000
0$
#1255000
0M
0L
0K
0J
1W
0V
0U
0T
b110000 "
b110000 ,
b110000 Q
b110000 R
0S
1$
#1260000
0$
#1265000
1J
b110001 "
b110001 ,
b110001 Q
b110001 R
1S
1$
#1270000
0$
#1275000
0J
1T
b110010 "
b110010 ,
b110010 Q
b110010 R
0S
1$
#1280000
0$
#1285000
1K
1J
b110011 "
b110011 ,
b110011 Q
b110011 R
1S
1$
#1290000
0$
#1295000
0K
0J
1U
0T
b110100 "
b110100 ,
b110100 Q
b110100 R
0S
1$
#1300000
0$
#1305000
1J
b110101 "
b110101 ,
b110101 Q
b110101 R
1S
1$
#1310000
0$
#1315000
0J
1T
b110110 "
b110110 ,
b110110 Q
b110110 R
0S
1$
#1320000
0$
#1325000
1L
1K
1J
b110111 "
b110111 ,
b110111 Q
b110111 R
1S
1$
#1330000
0L
0K
0J
0X
0W
0U
0T
b0 "
b0 ,
b0 Q
b0 R
0S
b0 #
b0 .
b0 >
b0 @
0A
1P
1?
0)
0$
1%
#1335000
b0 !
b0 *
b0 5
b0 4
0I
0/
b0 3
1$
#1340000
0P
0?
1)
0$
0%
