submissions/ARJUNGAUTAM_2023A3PS0209G_stopwatch/rt1/minutes_counter.v
module minutes_counter (
    input wire clk,
    input wire rst_n,   // Active-low reset
    input wire reset,
    input wire enable,  // Enable increment when seconds rollover
    output reg [7:0] minutes  // 0-255 minutes
);

// Counter logic
always @(posedge clk or negedge rst_n) begin
    if (!rst_n || reset) begin
        minutes <= 8'd0;
    end else if (enable) begin
        minutes <= minutes + 1'b1;
    end
end

endmodule

submissions/ARJUNGAUTAM_2023A3PS0209G_stopwatch/rt1/seconds_counter.v
module seconds_counter (
    input wire clk,
    input wire rst_n,   // Active-low reset
    input wire reset,
    input wire enable,  // Enable counting when running
    output reg [5:0] seconds,  // 0-59
    output reg rollover  // Signal to increment minutes
);

// Counter logic
always @(posedge clk or negedge rst_n) begin
    if (!rst_n || reset) begin
        seconds <= 6'd0;
        rollover <= 1'b0;
    end else if (enable) begin
        if (seconds == 6'd59) begin
            seconds <= 6'd0;
            rollover <= 1'b1;
        end else begin
            seconds <= seconds + 1'b1;
            rollover <= 1'b0;
        end
    end else begin
        rollover <= 1'b0;
    end
end

endmodule

submissions/ARJUNGAUTAM_2023A3PS0209G_stopwatch/rt1/control_fsm.v
module control_fsm (
    input wire clk,
    input wire rst_n,   // Active-low reset
    input wire start,
    input wire stop,
    input wire reset,
    output reg [1:0] status  // 00: IDLE, 01: RUNNING, 10: PAUSED
);

// State definitions
localparam IDLE = 2'b00;
localparam RUNNING = 2'b01;
localparam PAUSED = 2'b10;

// FSM logic
always @(posedge clk or negedge rst_n) begin
    if (!rst_n || reset) begin
        status <= IDLE;
    end else begin
        case (status)
            IDLE: begin
                if (start) begin
                    status <= RUNNING;
                end
            end
            RUNNING: begin
                if (stop) begin
                    status <= PAUSED;
                end
            end
            PAUSED: begin
                if (start) begin
                    status <= RUNNING;
                end
            end
            default: status <= IDLE;
        endcase
    end
end

endmodule

submissions/ARJUNGAUTAM_2023A3PS0209G_stopwatch/rt1/stopwatch_top.v
module stopwatch_top (
    input wire clk,
    input wire rst_n,   // active-low reset
    input wire start,
    input wire stop,
    input wire reset,
    output wire [7:0] minutes,
    output wire [5:0] seconds,
    output wire [1:0] status
);

// Internal signals
wire rollover;  // From seconds to minutes
wire running;   // Derived from status

// Instantiate FSM
control_fsm fsm_inst (
    .clk(clk),
    .rst_n(rst_n),
    .start(start),
    .stop(stop),
    .reset(reset),
    .status(status)
);

// Determine if running
assign running = (status == 2'b01);

// Instantiate seconds counter
seconds_counter sec_inst (
    .clk(clk),
    .rst_n(rst_n),
    .reset(reset),
    .enable(running),
    .seconds(seconds),
    .rollover(rollover)
);

// Instantiate minutes counter
minutes_counter min_inst (
    .clk(clk),
    .rst_n(rst_n),
    .reset(reset),
    .enable(rollover),
    .minutes(minutes)
);

endmodule

submissions/ARJUNGAUTAM_2023A3PS0209G_stopwatch/verilator_sw/stopwatch_waveform.vcd
$version Generated by VerilatedVcd $end
$date Mon Feb  2 13:47:08 2026
 $end
$timescale   1ps $end

 $scope module TOP $end
  $var wire  1 # clk $end
  $var wire  8 ( minutes [7:0] $end
  $var wire  1 ' reset $end
  $var wire  1 $ rst_n $end
  $var wire  6 ) seconds [5:0] $end
  $var wire  1 % start $end
  $var wire  2 * status [1:0] $end
  $var wire  1 & stop $end
  $scope module stopwatch_top $end
   $var wire  1 # clk $end
   $var wire  8 ( minutes [7:0] $end
   $var wire  1 ' reset $end
   $var wire  1 + rollover $end
   $var wire  1 $ rst_n $end
   $var wire  1 , running $end
   $var wire  6 ) seconds [5:0] $end
   $var wire  1 % start $end
   $var wire  2 * status [1:0] $end
   $var wire  1 & stop $end
   $scope module fsm_inst $end
    $var wire  2 - IDLE [1:0] $end
    $var wire  2 / PAUSED [1:0] $end
    $var wire  2 . RUNNING [1:0] $end
    $var wire  1 # clk $end
    $var wire  1 ' reset $end
    $var wire  1 $ rst_n $end
    $var wire  1 % start $end
    $var wire  2 * status [1:0] $end
    $var wire  1 & stop $end
   $upscope $end
   $scope module min_inst $end
    $var wire  1 # clk $end
    $var wire  1 + enable $end
    $var wire  8 ( minutes [7:0] $end
    $var wire  1 ' reset $end
    $var wire  1 $ rst_n $end
   $upscope $end
   $scope module sec_inst $end
    $var wire  1 # clk $end
    $var wire  1 , enable $end
    $var wire  1 ' reset $end
    $var wire  1 + rollover $end
    $var wire  1 $ rst_n $end
    $var wire  6 ) seconds [5:0] $end
   $upscope $end
  $upscope $end
 $upscope $end
$enddefinitions $end


#0
0#
0$
0%
0&
0'
b00000000 (
b000000 )
b00 *
0+
0,
b00 -
b01 .
b10 /
#1
1$
#2
1#
#4
0#
#6
1#
#8
0#
#10
1#
#12
0#
#14
1#
#16
0#
#18
1#
#20
0#
#22
1#
#24
0#
1%
#26
1#
b01 *
1,
#28
0#
0%
#30
1#
b000001 )
#32
0#
#34
1#
b000010 )
#36
0#
#38
1#
b000011 )
#40
0#
#42
1#
b000100 )
#44
0#
#46
1#
b000101 )
#48
0#
#50
1#
b000110 )
#52
0#
#54
1#
b000111 )
#56
0#
#58
1#
b001000 )
#60
0#
#62
1#
b001001 )
#64
0#
1&
#66
1#
b001010 )
b10 *
0,
#68
0#
0&
#70
1#
#72
0#
#74
1#
#76
0#
#78
1#
#80
0#
#82
1#
#84
0#
1%
#86
1#
b01 *
1,
#88
0#
0%
#90
1#
b001011 )
#92
0#
#94
1#
b001100 )
#96
0#
#98
1#
b001101 )
#100
0#
#102
1#
b001110 )
#104
0#
#106
1#
b001111 )
#108
0#
#110
1#
b010000 )
#112
0#
#114
1#
b010001 )
#116
0#
#118
1#
b010010 )
#120
0#
#122
1#
b010011 )
#124
0#
#126
1#
b010100 )
#128
0#
#130
1#
b010101 )
#132
0#
#134
1#
b010110 )
#136
0#
#138
1#
b010111 )
#140
0#
#142
1#
b011000 )
#144
0#
#146
1#
b011001 )
#148
0#
#150
1#
b011010 )
#152
0#
#154
1#
b011011 )
#156
0#
#158
1#
b011100 )
#160
0#
#162
1#
b011101 )
#164
0#
#166
1#
b011110 )
#168
0#
#170
1#
b011111 )
#172
0#
#174
1#
b100000 )
#176
0#
#178
1#
b100001 )
#180
0#
#182
1#
b100010 )
#184
0#
#186
1#
b100011 )
#188
0#
#190
1#
b100100 )
#192
0#
#194
1#
b100101 )
#196
0#
#198
1#
b100110 )
#200
0#
#202
1#
b100111 )
#204
0#
#206
1#
b101000 )
#208
0#
#210
1#
b101001 )
#212
0#
#214
1#
b101010 )
#216
0#
#218
1#
b101011 )
#220
0#
#222
1#
b101100 )
#224
0#
#226
1#
b101101 )
#228
0#
#230
1#
b101110 )
#232
0#
#234
1#
b101111 )
#236
0#
#238
1#
b110000 )
